README.txt
setup.cfg
setup.py
textutils.py
textutils.egg-info/PKG-INFO
textutils.egg-info/SOURCES.txt
textutils.egg-info/dependency_links.txt
textutils.egg-info/top_level.txt