Metadata-Version: 1.1
Name: textutils
Version: 0.1
Summary: Small collection of string and text utilities
Home-page: https://bitbucket.org/AluisioASG/textutils.py
Author: Aluísio Augusto Silva Gonçalves
Author-email: kalug@kalug.net
License: Public Domain (CC0)
Download-URL: https://bitbucket.org/AluisioASG/textutils.py/downloads
Platform: UNKNOWN
Classifier: Development Status :: 3 - Alpha
Classifier: Intended Audience :: Developers
Classifier: Intended Audience :: System Administrators
Classifier: License :: Public Domain
Classifier: Programming Language :: Python :: 2
Classifier: Programming Language :: Python :: 2.7
Classifier: Programming Language :: Python :: 3
Classifier: Programming Language :: Python :: 3.2
Classifier: Operating System :: OS Independent
Classifier: Topic :: Software Development :: Libraries :: Python Modules
